[
  {
    "Code": "DK6960.670.1",
    "listingType": "interhomeaccommocation",
    "title": "Ferienhaus \"Signhild\" - from the sea",
    "description": {
      "general": "Single-family house, built in 1985. 400 m from the sea. Private: natural state property 1'200 m2. Terrace (74 m2), children's playground. In the house: sauna. Parking at the house. Grocery 2 km. \"Signhild\" - from the sea\", 3-room house 67 m2. Object suitable for 6 adults. Living room with TV, video, radio, CD-player and hi-fi system. 1 room with 1 double bed. 1 room with 1 x 2 bunk beds. 1 room with 1 double bed. Kitchen (4 hot plates, oven, dishwasher, microwave, freezer). Shower/WC. Terrace 20 m2, roofed. Facilities: Internet (WiFi). Please note: non-smokers only. Maximum 1 pet/ dog allowed. 760-14223",
      "inside": "\"Signhild\" - from the sea\", 3-room house 67 m2. Object suitable for 6 adults. Living room with TV, video, radio, CD-player and hi-fi system. 1 room with 1 double bed. 1 room with 1 x 2 bunk beds. 1 room with 1 double bed. Kitchen (4 hot plates, oven, dishwasher, microwave, freezer). Shower/WC. Terrace 20 m2, roofed. Facilities: Internet (WiFi). Please note: non-smokers only. Maximum 1 pet/ dog allowed. 760-14223",
      "outside": "Single-family house, built in 1985. 400 m from the sea. Private: natural state property 1'200 m2. Terrace (74 m2), children's playground. In the house: sauna. Parking at the house. Grocery 2 km."
    },
    "checkInTime": "1400",
    "checkOutTime": "1000",
    "location": {
      "address": "Hvide Sande",
      "optional": "",
      "type": "Point",
      "coordinates": [
        "8.169328",
        "55.849335"
      ]
    },
    "pricePerNight": {
      "price": 0,
      "currency": "CHF"
    },
    "specialPrices": [],
    "additionalServices": [],
    "availability": [],
    "bedRooms": 3,
    "rooms": {
      "number": 3,
      "room": [
        {
          "floor": "MainFloor",
          "type": "rooms",
          "count": 3
        },
        {
          "floor": "MainFloor",
          "type": "living_room",
          "count": 1
        }
      ]
    },
    "washrooms": 1,
    "status": "active",
    "legal": {
      "cancellationPolicy": "Je nach Reisezeitraum 90% Rückerstattung bis 0% Rückerstattung.",
      "termsAndConditions": "https://www.waureisen.com/uploads/leeres-dokument-1741543223823.pdf"
    },
    "source": {
      "name": "interhome",
      "redirectLink": "https://www.interhome.ch/daenemark/juetlands-westkueste/hvide-sande/ferienhaus-signhild-from-the-sea-dk6960.670.1/?partnerid=CH1002557&iframe=true&layout=footer&color-thm=0096DB&color-cta=E63957&color-cta-contrast=FFFFFF"
    },
    "images": [
      "https://images.interhome.com/DK6960.670.1/partner-medium/B5FB3FD8F2441EEF8DF96DDCCAF69959",
      "https://images.interhome.com/DK6960.670.1/partner-medium/B5FB3FD8F2441EEF8DF96DDCCAF6B959",
      "https://images.interhome.com/DK6960.670.1/partner-medium/B5FB3FD8F2441EEF8DF96DDCCAF6D959",
      "https://images.interhome.com/DK6960.670.1/partner-medium/5A56365000CA1EDDAAF60C1E1283745C",
      "https://images.interhome.com/DK6960.670.1/partner-medium/5A56365000CA1EDDAAF60C1E1283945C",
      "https://images.interhome.com/DK6960.670.1/partner-medium/5A56365000CA1EDDAAF60C1E1283B45C",
      "https://images.interhome.com/DK6960.670.1/partner-medium/5A56365000CA1EDDAAF60C1E1283D45C",
      "https://images.interhome.com/DK6960.670.1/partner-medium/5A56365000CA1EDDAAF60C1E1283F45C",
      "https://images.interhome.com/DK6960.670.1/partner-medium/5A56365000CA1EDDAAF60C1E1284145C",
      "https://images.interhome.com/DK6960.670.1/partner-medium/5A56365000CA1EDDAAF60C1E1284345C",
      "https://images.interhome.com/DK6960.670.1/partner-medium/5A56365000CA1EDDAAF60C1E1284545C",
      "https://images.interhome.com/DK6960.670.1/partner-medium/B5FB3FD8F2441EEF8DF96DDCCAF6F959",
      "https://images.interhome.com/DK6960.670.1/partner-medium/B5FB3FD8F2441EEF8DF96DDCCAF71959",
      "https://images.interhome.com/DK6960.670.1/partner-medium/B5FB3FD8F2441EEF8DF96DDCCAF73959",
      "https://images.interhome.com/DK6960.670.1/partner-medium/B5FB3FD8F2441EEF8DF96DDCCAF75959",
      "https://images.interhome.com/DK6960.670.1/partner-medium/B5FB3FD8F2441EEF8DF96DDCCAF77959",
      "https://images.interhome.com/DK6960.670.1/partner-medium/B5FB3FD8F2441EEF8DF96DDCCAF79959",
      "https://images.interhome.com/DK6960.670.1/partner-medium/B5FB3FD8F2441EEF8DF96DDCCAF7B959",
      "https://images.interhome.com/DK6960.670.1/partner-medium/5A56365000CA1EDDAAF60C1E1284945C",
      "https://images.interhome.com/DK6960.670.1/partner-medium/B5FB3FD8F2441EEF8DF96DDCCAF7D959",
      "https://images.interhome.com/DK6960.670.1/partner-medium/B5FB3FD8F2441EEF8DF96DDCCAF7F959",
      "https://images.interhome.com/DK6960.670.1/partner-medium/B5FB3FD8F2441EEF8DF96DDCCAF81959",
      "https://images.interhome.com/DK6960.670.1/partner-medium/B5FB3FD8F2441EEF8DF96DDCCAF83959",
      "https://images.interhome.com/DK6960.670.1/partner-medium/B5FB3FD8F2441EEF8DF96DDCCAF85959",
      "https://images.interhome.com/DK6960.670.1/partner-medium/B5FB3FD8F2441EEF8DF96DDCCAF87959",
      "https://images.interhome.com/DK6960.670.1/partner-medium/B5FB3FD8F2441EEF8DF96DDCCAF89959",
      "https://images.interhome.com/DK6960.670.1/partner-medium/B5FB3FD8F2441EEF8DF96DDCCAF8B959",
      "https://images.interhome.com/DK6960.670.1/partner-medium/B5FB3FD8F2441EEF8DF96DDCCAF8D959",
      "https://images.interhome.com/DK6960.670.1/partner-medium/B5FB3FD8F2441EEF8DF96DDCCAF8F959",
      "https://images.interhome.com/DK6960.670.1/partner-medium/B5FB3FD8F2441EEF8DF96DDCCAF91959",
      "https://images.interhome.com/DK6960.670.1/partner-medium/FB6DD225384D1EDF8EDB5DA9509036B2"
    ],
    "attributes": [
      {
        "name": "cots"
      },
      {
        "name": "pets_max"
      },
      {
        "name": "studio"
      },
      {
        "name": "playground"
      },
      {
        "name": "cleaning"
      },
      {
        "name": "dishwasher"
      },
      {
        "name": "fireplace"
      },
      {
        "name": "microwave"
      },
      {
        "name": "oven"
      },
      {
        "name": "parking"
      },
      {
        "name": "pets"
      },
      {
        "name": "sauna"
      },
      {
        "name": "familyfriendly_summer"
      },
      {
        "name": "shower"
      },
      {
        "name": "terrace"
      },
      {
        "name": "fridge"
      },
      {
        "name": "heating"
      },
      {
        "name": "kitchen"
      },
      {
        "name": "freezer"
      },
      {
        "name": "nonsmoking"
      },
      {
        "name": "tv"
      },
      {
        "name": "stove"
      },
      {
        "name": "wlan"
      }
    ],
    "provider": "Interhome",
    "selectedFilters": {},
    "totalViews": 0,
    "totalBookings": 0,
    "totalReviews": 0,
    "totalRating": 0,
    "averageRating": 0,
    "createdAt": "2025-04-21T17:52:59.873Z",
    "updatedAt": "2025-04-21T17:52:59.873Z"
  },
  {
    "Code": "DK6960.611.1",
    "listingType": "interhomeaccommocation",
    "title": "Ferienhaus \"Skev\" - 200m to the inlet",
    "description": {
      "general": "Single-family house, built in 1999. 950 m from the sea. Private: natural state property 2'198 m2. Terrace (80 m2), barbecue. In the house: sauna, washing machine, tumble dryer. Parking at the house. Grocery 2 km. \"Skev\" - 200m to the inlet\", 3-room house 96 m2. Object suitable for 6 adults. Living room with TV and CD-player. 1 room with 2 beds. 1 room with 1 double bed. 1 room with 1 double bed. Kitchen (oven, dishwasher, 4 ceramic glass hob hotplates, microwave, freezer). Shower/WC, hydro massage bath. Terrace 4 m2, roofed. Facilities: Internet (WiFi). Please note: non-smokers only. Maximum 1 pet/ dog allowed. 760-14791",
      "inside": "\"Skev\" - 200m to the inlet\", 3-room house 96 m2. Object suitable for 6 adults. Living room with TV and CD-player. 1 room with 2 beds. 1 room with 1 double bed. 1 room with 1 double bed. Kitchen (oven, dishwasher, 4 ceramic glass hob hotplates, microwave, freezer). Shower/WC, hydro massage bath. Terrace 4 m2, roofed. Facilities: Internet (WiFi). Please note: non-smokers only. Maximum 1 pet/ dog allowed. 760-14791",
      "outside": "Single-family house, built in 1999. 950 m from the sea. Private: natural state property 2'198 m2. Terrace (80 m2), barbecue. In the house: sauna, washing machine, tumble dryer. Parking at the house. Grocery 2 km."
    },
    "checkInTime": "1400",
    "checkOutTime": "1000",
    "location": {
      "address": "Hvide Sande",
      "optional": "",
      "type": "Point",
      "coordinates": [
        "8.121076",
        "56.05501"
      ]
    },
    "pricePerNight": {
      "price": 0,
      "currency": "CHF"
    },
    "specialPrices": [],
    "additionalServices": [],
    "availability": [],
    "bedRooms": 3,
    "rooms": {
      "number": 3,
      "room": [
        {
          "floor": "MainFloor",
          "type": "rooms",
          "count": 3
        },
        {
          "floor": "MainFloor",
          "type": "living_room",
          "count": 1
        }
      ]
    },
    "washrooms": 1,
    "status": "active",
    "legal": {
      "cancellationPolicy": "Je nach Reisezeitraum 90% Rückerstattung bis 0% Rückerstattung.",
      "termsAndConditions": "https://www.waureisen.com/uploads/leeres-dokument-1741541879762.pdf"
    },
    "source": {
      "name": "interhome",
      "redirectLink": "https://www.interhome.ch/daenemark/juetlands-westkueste/hvide-sande/ferienhaus-skev-200m-to-the-inlet-dk6960.611.1/?partnerid=CH1002557&iframe=true&layout=footer&color-thm=0096DB&color-cta=E63957&color-cta-contrast=FFFFFF"
    },
    "images": [
      "https://images.interhome.com/DK6960.611.1/partner-medium/F2D993D001441EDDAAF5DD48FC2E16C6",
      "https://images.interhome.com/DK6960.611.1/partner-medium/F2D993D001441EDDAAF5DD48FC2E36C6",
      "https://images.interhome.com/DK6960.611.1/partner-medium/F2D993D001441EDDAAF5DD48FC2E56C6",
      "https://images.interhome.com/DK6960.611.1/partner-medium/F2D993D001441EDDAAF5DD48FC2E76C6",
      "https://images.interhome.com/DK6960.611.1/partner-medium/F2D993D001441EDDAAF5DD48FC2E96C6",
      "https://images.interhome.com/DK6960.611.1/partner-medium/F2D993D001441EDDAAF5DD48FC2EB6C6",
      "https://images.interhome.com/DK6960.611.1/partner-medium/F2D993D001441EDDAAF5DD48FC2ED6C6",
      "https://images.interhome.com/DK6960.611.1/partner-medium/F2D993D001441EDDAAF5DD48FC2EF6C6",
      "https://images.interhome.com/DK6960.611.1/partner-medium/F2D993D001441EDDAAF5DD48FC2F16C6",
      "https://images.interhome.com/DK6960.611.1/partner-medium/F2D993D001441EDDAAF5DD48FC2F36C6",
      "https://images.interhome.com/DK6960.611.1/partner-medium/F2D993D001441EDDAAF5DD48FC2F56C6",
      "https://images.interhome.com/DK6960.611.1/partner-medium/F2D993D001441EDDAAF5DD48FC2F76C6",
      "https://images.interhome.com/DK6960.611.1/partner-medium/F2D993D001441EDDAAF5DD48FC2F96C6",
      "https://images.interhome.com/DK6960.611.1/partner-medium/F2D993D001441EDDAAF5DD48FC2FB6C6",
      "https://images.interhome.com/DK6960.611.1/partner-medium/F2D993D001441EDDAAF5DD48FC2FD6C6",
      "https://images.interhome.com/DK6960.611.1/partner-medium/F2D993D001441EDDAAF5DD48FC2FF6C6",
      "https://images.interhome.com/DK6960.611.1/partner-medium/F2D993D001441EDDAAF5DD48FC3016C6",
      "https://images.interhome.com/DK6960.611.1/partner-medium/F2D993D001441EDDAAF5DD48FC3036C6",
      "https://images.interhome.com/DK6960.611.1/partner-medium/F2D993D001441EDDAAF5DD48FC3056C6",
      "https://images.interhome.com/DK6960.611.1/partner-medium/07235D67CE761EEF80E07CF263735959",
      "https://images.interhome.com/DK6960.611.1/partner-medium/07235D67CE761EEF80E07CF263737959",
      "https://images.interhome.com/DK6960.611.1/partner-medium/07235D67CE761EEF80E07CF263739959",
      "https://images.interhome.com/DK6960.611.1/partner-medium/07235D67CE761EEF80E07CF26373B959",
      "https://images.interhome.com/DK6960.611.1/partner-medium/07235D67CE761EEF80E07CF26373D959",
      "https://images.interhome.com/DK6960.611.1/partner-medium/07235D67CE761EEF80E07CF26373F959",
      "https://images.interhome.com/DK6960.611.1/partner-medium/07235D67CE761EEF80E07CF263741959",
      "https://images.interhome.com/DK6960.611.1/partner-medium/07235D67CE761EEF80E07CF263743959",
      "https://images.interhome.com/DK6960.611.1/partner-medium/07235D67CE761EEF80E07CF263745959",
      "https://images.interhome.com/DK6960.611.1/partner-medium/07235D67CE761EEF80E07CF263747959",
      "https://images.interhome.com/DK6960.611.1/partner-medium/07235D67CE761EEF80E07CF263749959",
      "https://images.interhome.com/DK6960.611.1/partner-medium/FB6DD225384D1EDF8EDB5AB58DBB76B2"
    ],
    "attributes": [
      {
        "name": "cots"
      },
      {
        "name": "pets_max"
      },
      {
        "name": "studio"
      },
      {
        "name": "bbq"
      },
      {
        "name": "cleaning"
      },
      {
        "name": "cook"
      },
      {
        "name": "dishwasher"
      },
      {
        "name": "tumbler"
      },
      {
        "name": "fireplace"
      },
      {
        "name": "microwave"
      },
      {
        "name": "parking"
      },
      {
        "name": "pets"
      },
      {
        "name": "sauna"
      },
      {
        "name": "familyfriendly_summer"
      },
      {
        "name": "shower"
      },
      {
        "name": "terrace"
      },
      {
        "name": "washingmachine"
      },
      {
        "name": "fridge"
      },
      {
        "name": "heating"
      },
      {
        "name": "kitchen"
      },
      {
        "name": "freezer"
      },
      {
        "name": "nonsmoking"
      },
      {
        "name": "tv"
      },
      {
        "name": "stove"
      },
      {
        "name": "wlan"
      }
    ],
    "provider": "Interhome",
    "selectedFilters": {},
    "totalViews": 0,
    "totalBookings": 0,
    "totalReviews": 0,
    "totalRating": 0,
    "averageRating": 0,
    "createdAt": "2025-04-21T17:53:00.281Z",
    "updatedAt": "2025-04-21T17:53:00.281Z"
  },
  {
    "Code": "DK9990.650.1",
    "listingType": "interhomeaccommocation",
    "title": "Ferienhaus \"Gunulf\" - 150m from the sea",
    "description": {
      "general": "Single-family house, built in 1844. 150 m from the sea. For shared use: garden. Private: natural state property 280 m2, garden (fenced). Terrace (100 m2). In the house: washing machine. Parking at the house. Grocery 200 m. The owner does not accept any youth groups. \"Gunulf\" - 150m from the sea\", 3-room house 100 m2. Object suitable for 6 adults. Living room with TV and radio. 1 room with 1 double bed. Kitchen (oven, dishwasher, 4 induction hot plates, freezer). Shower/WC. Upper floor: living room with 1 double bed. 1 room with 2 beds. Facilities: Internet (WiFi). Please note: non-smokers only. Maximum 1 pet/ dog allowed. Bookings accepted for holiday purposes only. 813-175937",
      "inside": "\"Gunulf\" - 150m from the sea\", 3-room house 100 m2. Object suitable for 6 adults. Living room with TV and radio. 1 room with 1 double bed. Kitchen (oven, dishwasher, 4 induction hot plates, freezer). Shower/WC. Upper floor: living room with 1 double bed. 1 room with 2 beds. Facilities: Internet (WiFi). Please note: non-smokers only. Maximum 1 pet/ dog allowed. Bookings accepted for holiday purposes only. 813-175937",
      "outside": "Single-family house, built in 1844. 150 m from the sea. For shared use: garden. Private: natural state property 280 m2, garden (fenced). Terrace (100 m2). In the house: washing machine. Parking at the house. Grocery 200 m. The owner does not accept any youth groups."
    },
    "checkInTime": "1400",
    "checkOutTime": "1000",
    "location": {
      "address": "Skagen",
      "optional": "",
      "type": "Point",
      "coordinates": [
        "10.602262",
        "57.725147"
      ]
    },
    "pricePerNight": {
      "price": 0,
      "currency": "CHF"
    },
    "specialPrices": [],
    "additionalServices": [],
    "availability": [],
    "bedRooms": 2,
    "rooms": {
      "number": 3,
      "room": [
        {
          "floor": "MainFloor",
          "type": "rooms",
          "count": 1
        },
        {
          "floor": "UpperFloor",
          "type": "living_room",
          "count": 1
        },
        {
          "floor": "MainFloor",
          "type": "rooms",
          "count": 1
        },
        {
          "floor": "MainFloor",
          "type": "living_room",
          "count": 1
        }
      ]
    },
    "washrooms": 1,
    "status": "active",
    "legal": {
      "cancellationPolicy": "Je nach Reisezeitraum 90% Rückerstattung bis 0% Rückerstattung.",
      "termsAndConditions": "https://www.waureisen.com/uploads/leeres-dokument-1741540632481.pdf"
    },
    "source": {
      "name": "interhome",
      "redirectLink": "https://www.interhome.ch/daenemark/nordwestjuetland/skagen/ferienhaus-gunulf-150m-from-the-sea-dk9990.650.1/?partnerid=CH1002557&iframe=true&layout=footer&color-thm=0096DB&color-cta=E63957&color-cta-contrast=FFFFFF"
    },
    "images": [
      "https://images.interhome.com/DK9990.650.1/partner-medium/5A56365000CA1EEDAEA13C55DA44CA96",
      "https://images.interhome.com/DK9990.650.1/partner-medium/5A56365000CA1EEDAEA13C55DA44EA96",
      "https://images.interhome.com/DK9990.650.1/partner-medium/5A56365000CA1EEDAEA13C55DA450A96",
      "https://images.interhome.com/DK9990.650.1/partner-medium/5A56365000CA1EEDAEA13C55DA452A96",
      "https://images.interhome.com/DK9990.650.1/partner-medium/5A56365000CA1EEDAEA13C55DA454A96",
      "https://images.interhome.com/DK9990.650.1/partner-medium/5A56365000CA1EEDAEA13C55DA456A96",
      "https://images.interhome.com/DK9990.650.1/partner-medium/5A56365000CA1EEDAEA13C55DA458A96",
      "https://images.interhome.com/DK9990.650.1/partner-medium/5A56365000CA1EEDAEA13C55DA45AA96",
      "https://images.interhome.com/DK9990.650.1/partner-medium/5A56365000CA1EEDAEA13C55DA45CA96",
      "https://images.interhome.com/DK9990.650.1/partner-medium/5A56365000CA1EEDAEA13C55DA45EA96",
      "https://images.interhome.com/DK9990.650.1/partner-medium/5A56365000CA1EEDAEA13C55DA460A96",
      "https://images.interhome.com/DK9990.650.1/partner-medium/5A56365000CA1EEDAEA13C55DA462A96",
      "https://images.interhome.com/DK9990.650.1/partner-medium/5A56365000CA1EEDAEA13C55DA464A96",
      "https://images.interhome.com/DK9990.650.1/partner-medium/5A56365000CA1EEDAEA13C55DA466A96",
      "https://images.interhome.com/DK9990.650.1/partner-medium/5A56365000CA1EEDAEA13C55DA468A96",
      "https://images.interhome.com/DK9990.650.1/partner-medium/5A56365000CA1EEDAEA13C55DA46AA96",
      "https://images.interhome.com/DK9990.650.1/partner-medium/5A56365000CA1EEDAEA13C55DA46CA96",
      "https://images.interhome.com/DK9990.650.1/partner-medium/5A56365000CA1EEDAEA13C55DA46EA96",
      "https://images.interhome.com/DK9990.650.1/partner-medium/5A56365000CA1EEDAEA13C55DA470A96",
      "https://images.interhome.com/DK9990.650.1/partner-medium/5A56365000CA1EEDAEA13C55DA472A96",
      "https://images.interhome.com/DK9990.650.1/partner-medium/5A56365000CA1EEDAEA13C55DA474A96",
      "https://images.interhome.com/DK9990.650.1/partner-medium/D1EDF379EB701EDF8EDB649BAC5432B9"
    ],
    "attributes": [
      {
        "name": "cots"
      },
      {
        "name": "pets_max"
      },
      {
        "name": "studio"
      },
      {
        "name": "cleaning"
      },
      {
        "name": "cook"
      },
      {
        "name": "dishwasher"
      },
      {
        "name": "parking"
      },
      {
        "name": "pets"
      },
      {
        "name": "familyfriendly_summer"
      },
      {
        "name": "shower"
      },
      {
        "name": "terrace"
      },
      {
        "name": "washingmachine"
      },
      {
        "name": "fridge"
      },
      {
        "name": "heating"
      },
      {
        "name": "kitchen"
      },
      {
        "name": "no_youth_groups"
      },
      {
        "name": "freezer"
      },
      {
        "name": "nonsmoking"
      },
      {
        "name": "tv"
      },
      {
        "name": "stove"
      },
      {
        "name": "wlan"
      }
    ],
    "provider": "Interhome",
    "selectedFilters": {},
    "totalViews": 0,
    "totalBookings": 0,
    "totalReviews": 0,
    "totalRating": 0,
    "averageRating": 0,
    "createdAt": "2025-04-21T17:53:00.707Z",
    "updatedAt": "2025-04-21T17:53:00.707Z"
  },
  {
    "Code": "DK6960.604.1",
    "listingType": "interhomeaccommocation",
    "title": "Ferienhaus \"Gottfreda\" - 330m to the inlet",
    "description": {
      "general": "Single-family house, built in 1991. 930 m from the sea. Private: natural state property 2'500 m2. Terrace (32 m2), children's playground (swing). In the house: sauna, washing machine, tumble dryer. Parking at the house. E-charging station. Grocery 3 km. The owner does not accept any youth groups. \"Gottfreda\" - 330m to the inlet\", 4-room house 125 m2. Object suitable for 10 adults + 1 child. Living room with TV, radio, CD-player, hi-fi system and DVD. 1 room with 1 double bed. 1 room with 2 x 2 bunk beds. 1 room with 1 double bed. 1 room with 1 double bed. Kitchen (oven, dishwasher, 4 ceramic glass hob hotplates, microwave, freezer). 2 showers/WC, hydro massage bath. Terrace 18 m2, roofed. Facilities: children's high chair, baby cot. Internet (WiFi). Please note: non-smokers only. Maximum 1 pet/ dog allowed. 760-15458",
      "inside": "\"Gottfreda\" - 330m to the inlet\", 4-room house 125 m2. Object suitable for 10 adults + 1 child. Living room with TV, radio, CD-player, hi-fi system and DVD. 1 room with 1 double bed. 1 room with 2 x 2 bunk beds. 1 room with 1 double bed. 1 room with 1 double bed. Kitchen (oven, dishwasher, 4 ceramic glass hob hotplates, microwave, freezer). 2 showers/WC, hydro massage bath. Terrace 18 m2, roofed. Facilities: children's high chair, baby cot. Internet (WiFi). Please note: non-smokers only. Maximum 1 pet/ dog allowed. 760-15458",
      "outside": "Single-family house, built in 1991. 930 m from the sea. Private: natural state property 2'500 m2. Terrace (32 m2), children's playground (swing). In the house: sauna, washing machine, tumble dryer. Parking at the house. E-charging station. Grocery 3 km. The owner does not accept any youth groups."
    },
    "checkInTime": "1400",
    "checkOutTime": "1000",
    "location": {
      "address": "Hvide Sande",
      "optional": "",
      "type": "Point",
      "coordinates": [
        "8.162031",
        "55.930504"
      ]
    },
    "pricePerNight": {
      "price": 0,
      "currency": "CHF"
    },
    "specialPrices": [],
    "additionalServices": [],
    "availability": [],
    "bedRooms": 4,
    "rooms": {
      "number": 4,
      "room": [
        {
          "floor": "MainFloor",
          "type": "rooms",
          "count": 4
        },
        {
          "floor": "MainFloor",
          "type": "living_room",
          "count": 1
        }
      ]
    },
    "washrooms": 2,
    "status": "active",
    "legal": {
      "cancellationPolicy": "Je nach Reisezeitraum 90% Rückerstattung bis 0% Rückerstattung.",
      "termsAndConditions": "https://www.waureisen.com/uploads/leeres-dokument-1741539337928.pdf"
    },
    "source": {
      "name": "interhome",
      "redirectLink": "https://www.interhome.ch/daenemark/juetlands-westkueste/hvide-sande/ferienhaus-gottfreda-330m-to-the-inlet-dk6960.604.1/?partnerid=CH1002557&iframe=true&layout=footer&color-thm=0096DB&color-cta=E63957&color-cta-contrast=FFFFFF"
    },
    "images": [
      "https://images.interhome.com/DK6960.604.1/partner-medium/5A56365000C61EDDAAF5D74824418784",
      "https://images.interhome.com/DK6960.604.1/partner-medium/5A56365000C61EDDAAF5D7482441A784",
      "https://images.interhome.com/DK6960.604.1/partner-medium/5A56365000C61EDDAAF5D7482441C784",
      "https://images.interhome.com/DK6960.604.1/partner-medium/5A56365000C61EDDAAF5D7482441E784",
      "https://images.interhome.com/DK6960.604.1/partner-medium/5A56365000C61EDDAAF5D74824420784",
      "https://images.interhome.com/DK6960.604.1/partner-medium/5A56365000C61EDDAAF5D74824422784",
      "https://images.interhome.com/DK6960.604.1/partner-medium/5A56365000C61EDDAAF5D74824424784",
      "https://images.interhome.com/DK6960.604.1/partner-medium/5A56365000C61EDDAAF5D74824426784",
      "https://images.interhome.com/DK6960.604.1/partner-medium/5A56365000C61EDDAAF5D74824428784",
      "https://images.interhome.com/DK6960.604.1/partner-medium/5A56365000C61EDDAAF5D7482442A784",
      "https://images.interhome.com/DK6960.604.1/partner-medium/5A56365000C61EDDAAF5D7482442C784",
      "https://images.interhome.com/DK6960.604.1/partner-medium/5A56365000C61EDDAAF5D7482442E784",
      "https://images.interhome.com/DK6960.604.1/partner-medium/5A56365000C61EDDAAF5D74824430784",
      "https://images.interhome.com/DK6960.604.1/partner-medium/5A56365000C61EDDAAF5D74824432784",
      "https://images.interhome.com/DK6960.604.1/partner-medium/5A56365000C61EDDAAF5D74824434784",
      "https://images.interhome.com/DK6960.604.1/partner-medium/5A56365000C61EDDAAF5D74824436784",
      "https://images.interhome.com/DK6960.604.1/partner-medium/5A56365000C61EDDAAF5D74824438784",
      "https://images.interhome.com/DK6960.604.1/partner-medium/5A56365000C61EDDAAF5D7482443A784",
      "https://images.interhome.com/DK6960.604.1/partner-medium/5A56365000C61EDDAAF5D7482443C784",
      "https://images.interhome.com/DK6960.604.1/partner-medium/098AADC441DC1EDEBDFE5602EEA5D2B9",
      "https://images.interhome.com/DK6960.604.1/partner-medium/098AADC441DC1EDEBDFE5602EEA5F2B9",
      "https://images.interhome.com/DK6960.604.1/partner-medium/5A56365000C61EDDAAF5D74824442784",
      "https://images.interhome.com/DK6960.604.1/partner-medium/5A56365000C61EDDAAF5D74824444784",
      "https://images.interhome.com/DK6960.604.1/partner-medium/5A56365000C61EDDAAF5D74824446784",
      "https://images.interhome.com/DK6960.604.1/partner-medium/5A56365000C61EDDAAF5D74824448784",
      "https://images.interhome.com/DK6960.604.1/partner-medium/5A56365000C61EDDAAF5D7482444A784",
      "https://images.interhome.com/DK6960.604.1/partner-medium/5A56365000C61EDDAAF5D7482444C784",
      "https://images.interhome.com/DK6960.604.1/partner-medium/098AADC441DC1EDEBDFE5602EEA612B9",
      "https://images.interhome.com/DK6960.604.1/partner-medium/098AADC441DC1EDEBDFE5602EEA632B9",
      "https://images.interhome.com/DK6960.604.1/partner-medium/5A56365000C61EDDAAF5D74824452784",
      "https://images.interhome.com/DK6960.604.1/partner-medium/098AADC441DC1EDEBDFE5602EEA652B9",
      "https://images.interhome.com/DK6960.604.1/partner-medium/098AADC441DC1EDEBDFE5602EEA672B9",
      "https://images.interhome.com/DK6960.604.1/partner-medium/098AADC441DC1EDEBDFE5602EEA692B9",
      "https://images.interhome.com/DK6960.604.1/partner-medium/098AADC441DC1EDEBDFE5602EEA6B2B9",
      "https://images.interhome.com/DK6960.604.1/partner-medium/6B7798187DEF1FE086A8276160AED9CB"
    ],
    "attributes": [
      {
        "name": "cots"
      },
      {
        "name": "electric_vehiclecharging_stat"
      },
      {
        "name": "pets_max"
      },
      {
        "name": "studio"
      },
      {
        "name": "playground"
      },
      {
        "name": "cleaning"
      },
      {
        "name": "cook"
      },
      {
        "name": "dishwasher"
      },
      {
        "name": "tumbler"
      },
      {
        "name": "fireplace"
      },
      {
        "name": "microwave"
      },
      {
        "name": "parking"
      },
      {
        "name": "pets"
      },
      {
        "name": "sauna"
      },
      {
        "name": "familyfriendly_summer"
      },
      {
        "name": "shower"
      },
      {
        "name": "terrace"
      },
      {
        "name": "washingmachine"
      },
      {
        "name": "dvdplayer"
      },
      {
        "name": "fridge"
      },
      {
        "name": "heating"
      },
      {
        "name": "kitchen"
      },
      {
        "name": "no_youth_groups"
      },
      {
        "name": "freezer"
      },
      {
        "name": "nonsmoking"
      },
      {
        "name": "tv"
      },
      {
        "name": "stove"
      },
      {
        "name": "wlan"
      }
    ],
    "provider": "Interhome",
    "selectedFilters": {},
    "totalViews": 0,
    "totalBookings": 0,
    "totalReviews": 0,
    "totalRating": 0,
    "averageRating": 0,
    "createdAt": "2025-04-21T17:53:01.116Z",
    "updatedAt": "2025-04-21T17:53:01.116Z"
  },
  {
    "Code": "DK6792.626.1",
    "listingType": "interhomeaccommocation",
    "title": "Ferienhaus \"Heralda\" - 3.3km from the sea",
    "description": {
      "general": "Single-family house, built in 1990. 3.3 km from the sea. Private: natural state property 2'600 m2. Terrace (50 m2), children's playground (swing). In the house: sauna, washing machine. Parking at the house. Grocery 1.1 km. The owner does not accept any youth groups. \"Heralda\" - 3.3km from the sea\", 4-room house 105 m2. Object suitable for 8 adults. Living room with 1 double bed, TV, video and radio. 1 room with 1 double bed. 1 room with 2 beds. 1 room with 1 double bed. Kitchen (4 hot plates, oven, dishwasher, microwave, freezer). Shower/WC. Terrace 6 m2, roofed. Facilities: children's high chair. Internet (WiFi). Please note: non-smokers only. Maximum 3 pets/ dogs allowed. 550-9662",
      "inside": "\"Heralda\" - 3.3km from the sea\", 4-room house 105 m2. Object suitable for 8 adults. Living room with 1 double bed, TV, video and radio. 1 room with 1 double bed. 1 room with 2 beds. 1 room with 1 double bed. Kitchen (4 hot plates, oven, dishwasher, microwave, freezer). Shower/WC. Terrace 6 m2, roofed. Facilities: children's high chair. Internet (WiFi). Please note: non-smokers only. Maximum 3 pets/ dogs allowed. 550-9662",
      "outside": "Single-family house, built in 1990. 3.3 km from the sea. Private: natural state property 2'600 m2. Terrace (50 m2), children's playground (swing). In the house: sauna, washing machine. Parking at the house. Grocery 1.1 km. The owner does not accept any youth groups."
    },
    "checkInTime": "1400",
    "checkOutTime": "1000",
    "location": {
      "address": "Rømø",
      "optional": "",
      "type": "Point",
      "coordinates": [
        "8.538866",
        "55.13085"
      ]
    },
    "pricePerNight": {
      "price": 0,
      "currency": "CHF"
    },
    "specialPrices": [],
    "additionalServices": [],
    "availability": [],
    "bedRooms": 3,
    "rooms": {
      "number": 4,
      "room": [
        {
          "floor": "MainFloor",
          "type": "rooms",
          "count": 3
        },
        {
          "floor": "MainFloor",
          "type": "living_room",
          "count": 1
        }
      ]
    },
    "washrooms": 2,
    "status": "active",
    "legal": {
      "cancellationPolicy": "Je nach Reisezeitraum 90% Rückerstattung bis 0% Rückerstattung.",
      "termsAndConditions": "https://www.waureisen.com/uploads/leeres-dokument-1741538045425.pdf"
    },
    "source": {
      "name": "interhome",
      "redirectLink": "https://www.interhome.ch/daenemark/juetlands-westkueste/romo/ferienhaus-heralda-3-3km-from-the-sea-dk6792.626.1/?partnerid=CH1002557&iframe=true&layout=footer&color-thm=0096DB&color-cta=E63957&color-cta-contrast=FFFFFF"
    },
    "images": [
      "https://images.interhome.com/DK6792.626.1/partner-medium/F2D993D001441EEDAAAED71C37BF95B2",
      "https://images.interhome.com/DK6792.626.1/partner-medium/F2D993D001441EEDAAAED71C37BFB5B2",
      "https://images.interhome.com/DK6792.626.1/partner-medium/F2D993D001441EEDAAAED71C37BFD5B2",
      "https://images.interhome.com/DK6792.626.1/partner-medium/F2D993D001441EEDAAAED71C37BFF5B2",
      "https://images.interhome.com/DK6792.626.1/partner-medium/F2D993D001441EEDAAAED71C37C015B2",
      "https://images.interhome.com/DK6792.626.1/partner-medium/F2D993D001441EEDAAAED71C37C035B2",
      "https://images.interhome.com/DK6792.626.1/partner-medium/F2D993D001441EEDAAAED71C37C055B2",
      "https://images.interhome.com/DK6792.626.1/partner-medium/F2D993D001441EEDAAAED71C37C075B2",
      "https://images.interhome.com/DK6792.626.1/partner-medium/F2D993D001441EEDAAAED71C37C095B2",
      "https://images.interhome.com/DK6792.626.1/partner-medium/F2D993D001441EEDAAAED71C37C0B5B2",
      "https://images.interhome.com/DK6792.626.1/partner-medium/F2D993D001441EEDAAAED71C37C0D5B2",
      "https://images.interhome.com/DK6792.626.1/partner-medium/F2D993D001441EEDAAAED71C37C0F5B2",
      "https://images.interhome.com/DK6792.626.1/partner-medium/F2D993D001441EEDAAAED71C37C115B2",
      "https://images.interhome.com/DK6792.626.1/partner-medium/F2D993D001441EEDAAAED71C37C135B2",
      "https://images.interhome.com/DK6792.626.1/partner-medium/F2D993D001441EEDAAAED71C37C155B2",
      "https://images.interhome.com/DK6792.626.1/partner-medium/B711B55044371EDFBBBADDAC70F1F31A",
      "https://images.interhome.com/DK6792.626.1/partner-medium/B711B55044371EDFBBBADDAC70F2131A",
      "https://images.interhome.com/DK6792.626.1/partner-medium/F2D993D001441EEDAAAED71C37C1B5B2",
      "https://images.interhome.com/DK6792.626.1/partner-medium/F2D993D001441EEDAAAED71C37C1D5B2",
      "https://images.interhome.com/DK6792.626.1/partner-medium/F2D993D001441EEDAAAED71C37C1F5B2",
      "https://images.interhome.com/DK6792.626.1/partner-medium/F2D993D001441EEDAAAED71C37C215B2",
      "https://images.interhome.com/DK6792.626.1/partner-medium/F2D993D001441EEDAAAED71C37C235B2",
      "https://images.interhome.com/DK6792.626.1/partner-medium/F2D993D001441EEDAAAED71C37C255B2",
      "https://images.interhome.com/DK6792.626.1/partner-medium/F2D993D001441EEDAAAED71C37C275B2",
      "https://images.interhome.com/DK6792.626.1/partner-medium/F2D993D001441EEDAAAED71C37C295B2",
      "https://images.interhome.com/DK6792.626.1/partner-medium/F2D993D001441EEDAAAED71C37C2B5B2",
      "https://images.interhome.com/DK6792.626.1/partner-medium/F2D993D001441EEDAAAED71C37C2D5B2",
      "https://images.interhome.com/DK6792.626.1/partner-medium/B711B55044371EDFBBBADDAC70F2331A"
    ],
    "attributes": [
      {
        "name": "cots"
      },
      {
        "name": "pets_max"
      },
      {
        "name": "studio"
      },
      {
        "name": "cleaning"
      },
      {
        "name": "dishwasher"
      },
      {
        "name": "fireplace"
      },
      {
        "name": "microwave"
      },
      {
        "name": "oven"
      },
      {
        "name": "parking"
      },
      {
        "name": "pets"
      },
      {
        "name": "sauna"
      },
      {
        "name": "familyfriendly_summer"
      },
      {
        "name": "shower"
      },
      {
        "name": "terrace"
      },
      {
        "name": "washingmachine"
      },
      {
        "name": "fridge"
      },
      {
        "name": "heating"
      },
      {
        "name": "kitchen"
      },
      {
        "name": "no_youth_groups"
      },
      {
        "name": "freezer"
      },
      {
        "name": "nonsmoking"
      },
      {
        "name": "tv"
      },
      {
        "name": "stove"
      },
      {
        "name": "wlan"
      }
    ],
    "provider": "Interhome",
    "selectedFilters": {},
    "totalViews": 0,
    "totalBookings": 0,
    "totalReviews": 0,
    "totalRating": 0,
    "averageRating": 0,
    "createdAt": "2025-04-21T17:53:01.525Z",
    "updatedAt": "2025-04-21T17:53:01.525Z"
  }
]